jpm/__init__.py
jpm/cli.py
jpm/main.py
jpm-1.0.1.data/scripts/jpm
jpm-1.0.1.dist-info/LICENSE
jpm-1.0.1.dist-info/METADATA
jpm-1.0.1.dist-info/WHEEL
jpm-1.0.1.dist-info/top_level.txt
jpm-1.0.1.dist-info/RECORD
