Metadata-Version: 2.1
Name: jpm
Version: 1.0.1
Summary: A small CLI package manager for Java projects using Maven
Home-page: https://github.com/bbenefield89/Java_Package_Manager
Author: Brandon Benefield
Author-email: bsquared18@gmail.com
License: UNKNOWN
Platform: UNKNOWN
Classifier: Programming Language :: Python :: 3
Classifier: License :: OSI Approved :: MIT License
Classifier: Operating System :: OS Independent
